scrapester/__init__.py
scrapester/crawler.py
scrapester-0.1.2.dist-info/METADATA
scrapester-0.1.2.dist-info/WHEEL
scrapester-0.1.2.dist-info/top_level.txt
scrapester-0.1.2.dist-info/RECORD
